Padevel/__init__.py
Padevel/Windows/Core.py
Padevel/Windows/__init__.py
Padevel/Windows/Dwmapi/__init__.py
Padevel/Windows/Gdi/__init__.py
Padevel/Windows/Winuser/__init__.py
Pallery/__init__.py
Pallery/__main__.py
Paperl/__init__.py
Paperl/__main__.py
Paperl/Paperc/__init__.py
Paperl/Papers/__init__.py
Paperl/Papers/builder.py
Paperl/Papers/papers.py
Paperl/Papert/__init__.py
Paperl/Papert/Widgets/__init__.py
Paperl/Papert/Widgets/application.py
Paperl/Papert/Widgets/titleBar.py
Paperl/Papert/Widgets/widget.py
Paperl/Papert/Widgets/window.py
Paperl/Paperui/__init__.py
Paperl/Paperui/Advanced/__init__.py
Paperl/Paperui/Advanced/animation.py
Paperl/Paperui/Advanced/animationWindows.py
Paperl/Paperui/Advanced/constant.py
Paperl/Paperui/Drawing/DTheme.py
Paperl/Paperui/Drawing/DWindow.py
Paperl/Paperui/Drawing/__init__.py
Paperl/Paperui/Extension/__init__.py
Paperl/Paperui/Extension/balloon.py
Paperl/Paperui/Extension/colorChooser.py
Paperl/Paperui/Extension/frameIX.py
Paperl/Paperui/Extension/resizeHandleIX.py
Paperl/Paperui/Extension/selectedCanvas.py
Paperl/Paperui/Extension/windowIX.py
Paperl/Paperui/Extension/childWindow/__init__.py
Paperl/Paperui/Extension/childWindow/childwindow.py
Paperl/Paperui/Extension/childWindow/full_xp.png
Paperl/Paperui/Extension/childWindow/gray_button.png
Paperl/Paperui/Extension/childWindow/gray_button_s.png
Paperl/Paperui/Extension/childWindow/green_button.png
Paperl/Paperui/Extension/childWindow/green_button_s.png
Paperl/Paperui/Extension/childWindow/red_button.png
Paperl/Paperui/Extension/childWindow/red_button_s.png
Paperl/Paperui/Extension/childWindow/red_xp.png
Paperl/Paperui/Extension/childWindow/temp_0full_xp.png
Paperl/Paperui/Extension/childWindow/temp_0green_button.png
Paperl/Paperui/Extension/childWindow/temp_0red_button.png
Paperl/Paperui/Extension/childWindow/temp_0red_xp.png
Paperl/Paperui/Extension/childWindow/temp_0white_xp.png
Paperl/Paperui/Extension/childWindow/temp_0yellow_button.png
Paperl-0.0.3.dist-info/METADATA
Paperl-0.0.3.dist-info/WHEEL
Paperl-0.0.3.dist-info/top_level.txt
Paperl-0.0.3.dist-info/RECORD
