Metadata-Version: 2.1
Name: Paperl
Version: 0.0.3
Summary: 使用tkinter开发高级GUI调试库
Author: XiangQinxi
Author-email: XiangQinxi@outlook.com
Classifier: Programming Language :: Python :: 3
Classifier: License :: OSI Approved :: MIT License
Classifier: Operating System :: OS Independent
Requires-Python: >=3.8
Requires-Dist: colorama
Requires-Dist: sv-ttk
Requires-Dist: plyer
Requires-Dist: tksvg
Requires-Dist: darkdetect
